pycorec/__init__.py
pycorec/pycorec.py
pycorec-2.0.8.dist-info/AUTHORS.rst
pycorec-2.0.8.dist-info/LICENSE
pycorec-2.0.8.dist-info/METADATA
pycorec-2.0.8.dist-info/WHEEL
pycorec-2.0.8.dist-info/entry_points.txt
pycorec-2.0.8.dist-info/top_level.txt
pycorec-2.0.8.dist-info/RECORD
