Metadata-Version: 2.1
Name: pycorec
Version: 2.0.8
Summary: Python Boilerplate contains all the boilerplate you need to create a Python package.
Home-page: https://github.com/tnku10/pycorec
Author: Yuto Tanaka
Author-email: tanaka.yuto.u10@gmail.com
Keywords: pycorec
Classifier: Development Status :: 2 - Pre-Alpha
Classifier: Intended Audience :: Developers
Classifier: Natural Language :: English
Classifier: Programming Language :: Python :: 3
Classifier: Programming Language :: Python :: 3.6
Classifier: Programming Language :: Python :: 3.7
Classifier: Programming Language :: Python :: 3.8
Classifier: Programming Language :: Python :: 3.9
Classifier: Programming Language :: Python :: 3.10
Classifier: Programming Language :: Python :: 3.11
Requires-Python: >=3.6
License-File: LICENSE
License-File: AUTHORS.rst
Requires-Dist: customtkinter (>=5.2.0)
Requires-Dist: packaging (>=23.2)
Requires-Dist: Pillow (>=10.0.0)
Requires-Dist: natsort (>=8.4.0)
Requires-Dist: openpyxl (>=3.1.2)
Requires-Dist: screeninfo (~=0.8.1)
Requires-Dist: opencv-python (~=4.8.1.78)
Requires-Dist: numpy (~=1.26.2)
Requires-Dist: pandas (~=2.1.3)
Requires-Dist: styleframe (~=4.2)
